{
  "type_description_msg": {
    "type_description": {
      "type_name": "px4_msgs/msg/VteAidSource1d",
      "fields": [
        {
          "name": "timestamp",
          "type": {
            "type_id": 9,
            "capacity": 0,
            "string_capacity": 0,
            "nested_type_name": ""
          },
          "default_value": ""
        },
        {
          "name": "timestamp_sample",
          "type": {
            "type_id": 9,
            "capacity": 0,
            "string_capacity": 0,
            "nested_type_name": ""
          },
          "default_value": ""
        },
        {
          "name": "time_last_predict",
          "type": {
            "type_id": 9,
            "capacity": 0,
            "string_capacity": 0,
            "nested_type_name": ""
          },
          "default_value": ""
        },
        {
          "name": "observation",
          "type": {
            "type_id": 10,
            "capacity": 0,
            "string_capacity": 0,
            "nested_type_name": ""
          },
          "default_value": ""
        },
        {
          "name": "observation_variance",
          "type": {
            "type_id": 10,
            "capacity": 0,
            "string_capacity": 0,
            "nested_type_name": ""
          },
          "default_value": ""
        },
        {
          "name": "innovation",
          "type": {
            "type_id": 10,
            "capacity": 0,
            "string_capacity": 0,
            "nested_type_name": ""
          },
          "default_value": ""
        },
        {
          "name": "innovation_variance",
          "type": {
            "type_id": 10,
            "capacity": 0,
            "string_capacity": 0,
            "nested_type_name": ""
          },
          "default_value": ""
        },
        {
          "name": "test_ratio",
          "type": {
            "type_id": 10,
            "capacity": 0,
            "string_capacity": 0,
            "nested_type_name": ""
          },
          "default_value": ""
        },
        {
          "name": "fusion_status",
          "type": {
            "type_id": 3,
            "capacity": 0,
            "string_capacity": 0,
            "nested_type_name": ""
          },
          "default_value": ""
        },
        {
          "name": "time_since_meas_ms",
          "type": {
            "type_id": 10,
            "capacity": 0,
            "string_capacity": 0,
            "nested_type_name": ""
          },
          "default_value": ""
        },
        {
          "name": "history_steps",
          "type": {
            "type_id": 3,
            "capacity": 0,
            "string_capacity": 0,
            "nested_type_name": ""
          },
          "default_value": ""
        }
      ]
    },
    "referenced_type_descriptions": []
  },
  "type_hashes": [
    {
      "type_name": "px4_msgs/msg/VteAidSource1d",
      "hash_string": "RIHS01_0179c6b67c962865c9dd71a925a91ea742fb7f2babf80d6c752a0b17e558b917"
    }
  ]
}